dbmisvc_stack/__init__.py
dbmisvc_stack/app.py
dbmisvc_stack/browser.py
dbmisvc_stack/cli.py
dbmisvc_stack/commands/__init__.py
dbmisvc_stack/commands/base.py
dbmisvc_stack/commands/build.py
dbmisvc_stack/commands/check.py
dbmisvc_stack/commands/checkout.py
dbmisvc_stack/commands/clean.py
dbmisvc_stack/commands/clone.py
dbmisvc_stack/commands/down.py
dbmisvc_stack/commands/init.py
dbmisvc_stack/commands/logs.py
dbmisvc_stack/commands/packages.py
dbmisvc_stack/commands/pull.py
dbmisvc_stack/commands/push.py
dbmisvc_stack/commands/reup.py
dbmisvc_stack/commands/secrets.py
dbmisvc_stack/commands/shell.py
dbmisvc_stack/commands/status.py
dbmisvc_stack/commands/test.py
dbmisvc_stack/commands/up.py
dbmisvc_stack/commands/update.py
dbmisvc_stack-1.0.1.dist-info/METADATA
dbmisvc_stack-1.0.1.dist-info/WHEEL
dbmisvc_stack-1.0.1.dist-info/entry_points.txt
dbmisvc_stack-1.0.1.dist-info/top_level.txt
dbmisvc_stack-1.0.1.dist-info/RECORD
