Metadata-Version: 2.1
Name: dbmisvc-stack
Version: 1.0.1
Summary: A command line program to facilitate development on a stack of containerized services
Home-page: https://github.com/hms-dbmi/dbmisvc-stack.git
Author: HMS DBMI Technology Core
Author-email: bryan_larson@hms.harvard.edu
License: BSD 2-Clause
Keywords: cli
Platform: UNKNOWN
Classifier: Intended Audience :: Developers
Classifier: Topic :: Utilities
Classifier: License :: Public Domain
Classifier: Natural Language :: English
Classifier: Operating System :: OS Independent
Classifier: Programming Language :: Python :: 3
Classifier: Programming Language :: Python :: 3.3
Classifier: Programming Language :: Python :: 3.4
Classifier: Programming Language :: Python :: 3.5
Classifier: Programming Language :: Python :: 3.6
Classifier: Programming Language :: Python :: 3.7
Classifier: Programming Language :: Python :: 3.8
Classifier: Programming Language :: Python :: 3.9
Requires-Dist: boto3 (>=1.13)
Requires-Dist: colorlog (>=4.0)
Requires-Dist: docker (>=3.7)
Requires-Dist: docopt (>=0.6)
Requires-Dist: python-dateutil (>=2.6)
Requires-Dist: PyYAML (>=5.1)
Provides-Extra: dev
Requires-Dist: coverage (==4.4.1) ; extra == 'dev'
Requires-Dist: nose (==1.3.7) ; extra == 'dev'
Requires-Dist: pytest (==3.2.1) ; extra == 'dev'
Requires-Dist: pytest-cov (==2.5.1) ; extra == 'dev'
Requires-Dist: pre-commit (>=2.3) ; extra == 'dev'
Requires-Dist: selenium (>=3.141.0) ; extra == 'dev'
Requires-Dist: splinter (>=0.13.0) ; extra == 'dev'
Provides-Extra: selenium
Requires-Dist: selenium (>=3.141.0) ; extra == 'selenium'
Requires-Dist: splinter (>=0.13.0) ; extra == 'selenium'
Provides-Extra: test
Requires-Dist: coverage (==4.4.1) ; extra == 'test'
Requires-Dist: nose (==1.3.7) ; extra == 'test'
Requires-Dist: pytest (==3.2.1) ; extra == 'test'
Requires-Dist: pytest-cov (==2.5.1) ; extra == 'test'
